{
  "parent": "minecraft:recipes/root",
  "rewards": {
    "recipes": [
      "machina:decompose_machinarium_from_machinarium_block"
    ]
  },
  "criteria": {
    "has_machinarium_block": {
      "trigger": "minecraft:inventory_changed",
      "conditions": {
        "items": [
          {
            "item": "machina:machinarium_block"
          }
        ]
      }
    },
    "has_the_recipe": {
      "trigger": "minecraft:recipe_unlocked",
      "conditions": {
        "recipe": "machina:decompose_machinarium_from_machinarium_block"
      }
    }
  },
  "requirements": [
    [
      "has_machinarium_block",
      "has_the_recipe"
    ]
  ]
}